imgbot.py
setup.py
imgbot.egg-info/PKG-INFO
imgbot.egg-info/SOURCES.txt
imgbot.egg-info/dependency_links.txt
imgbot.egg-info/requires.txt
imgbot.egg-info/top_level.txt