Metadata-Version: 1.0
Name: imgbot
Version: 1.3.3
Summary: Subreddit image downloader.
Home-page: https://github.com/Zane-/imgbot
Author: Zane Bilous
Author-email: zanebilous@gmail.com
License: MIT
Keywords: bot reddit images
Platform: any
